ReLERNN/__init__.py
ReLERNN/helpers.py
ReLERNN/imports.py
ReLERNN/manager.py
ReLERNN/networks.py
ReLERNN/sequenceBatchGenerator.py
ReLERNN/simulator.py
ReLERNN-0.2.data/scripts/ReLERNN_BSCORRECT
ReLERNN-0.2.data/scripts/ReLERNN_PREDICT
ReLERNN-0.2.data/scripts/ReLERNN_PREDICT_HOTSPOT
ReLERNN-0.2.data/scripts/ReLERNN_PREDICT_POOL
ReLERNN-0.2.data/scripts/ReLERNN_SIMULATE
ReLERNN-0.2.data/scripts/ReLERNN_SIMULATE_HOTSPOT
ReLERNN-0.2.data/scripts/ReLERNN_SIMULATE_POOL
ReLERNN-0.2.data/scripts/ReLERNN_TRAIN
ReLERNN-0.2.data/scripts/ReLERNN_TRAIN_HOTSPOT
ReLERNN-0.2.data/scripts/ReLERNN_TRAIN_POOL
ReLERNN-0.2.dist-info/LICENSE
ReLERNN-0.2.dist-info/METADATA
ReLERNN-0.2.dist-info/WHEEL
ReLERNN-0.2.dist-info/top_level.txt
ReLERNN-0.2.dist-info/RECORD
