Metadata-Version: 2.1
Name: ReLERNN
Version: 0.2
Summary: ReLERNN: Recombination Landscape Estimation using Recurrent Neural Networks
Home-page: https://github.com/kern-lab/ReLERNN/
Author: Jeffrey Adrion, Jared Galloway, Andrew Kern
Author-email: jeffreyadrion@gmail.com, jaredgalloway07@gmail.com, adk@uoregon.edu
License: MIT
Platform: UNKNOWN
Requires-Dist: msprime (>=0.7.4)
Requires-Dist: scikit-learn (>=0.22.1)
Requires-Dist: matplotlib (>=3.1.3)
Requires-Dist: scikit-allel (>=1.2.1)
